chonkie_core/__init__.py
chonkie_core/_chunk.cpython-311-x86_64-linux-gnu.so
chonkie_core/py.typed
chonkie_core-0.9.2.dist-info/METADATA
chonkie_core-0.9.2.dist-info/WHEEL
chonkie_core-0.9.2.dist-info/RECORD
